nxp_lite_tools/__about__.py
nxp_lite_tools/__init__.py
nxp_lite_tools/help
nxp_lite_tools-0.2.2.dist-info/METADATA
nxp_lite_tools-0.2.2.dist-info/WHEEL
nxp_lite_tools-0.2.2.dist-info/entry_points.txt
nxp_lite_tools-0.2.2.dist-info/top_level.txt
nxp_lite_tools-0.2.2.dist-info/RECORD
